distributed_systems/__init__.py
distributed_systems-0.1.0.dist-info/METADATA
distributed_systems-0.1.0.dist-info/WHEEL
distributed_systems-0.1.0.dist-info/entry_points.txt
distributed_systems-0.1.0.dist-info/RECORD
